uvrun/__init__.py
uvrun/cli.py
uvrun/config.py
uvrun/discover.py
uvrun-0.1.5.dist-info/METADATA
uvrun-0.1.5.dist-info/WHEEL
uvrun-0.1.5.dist-info/entry_points.txt
uvrun-0.1.5.dist-info/licenses/LICENSE
uvrun-0.1.5.dist-info/RECORD
