Metadata-Version: 2.4
Name: uvrun
Version: 0.1.5
Summary: Run Python scripts with inline metadata directly from URLs
Author-email: Simon Benedict <hi@sbenedict.dev>
License-File: LICENSE
Requires-Python: >=3.11
Requires-Dist: click>=8.1.7
Requires-Dist: requests>=2.31.0
Requires-Dist: rich>=13.7.0
Requires-Dist: tomli-w>=1.0.0
Provides-Extra: dev
Requires-Dist: build>=1.0.3; extra == 'dev'
Requires-Dist: pre-commit>=3.6.0; extra == 'dev'
Requires-Dist: ruff>=0.1.14; extra == 'dev'
Requires-Dist: twine>=4.0.2; extra == 'dev'
